Metadata-Version: 2.1
Name: offpele
Version: 0.3.1
Summary: Open Force Field to PELE
Home-page: http://github.com/martimunicoy/offpele
Author: Martí Municoy
Author-email: martimunicoy@gmail.com
License: MIT
Keywords: molecular mechanics,forcefield,potential energy
Platform: UNKNOWN
Classifier: Development Status :: 1 - Planning
Classifier: Natural Language :: English
Classifier: Environment :: Console
Classifier: Intended Audience :: Science/Research
Classifier: Topic :: Utilities
Classifier: License :: OSI Approved :: MIT License
Classifier: Programming Language :: Python :: 3
Classifier: Operating System :: Unix
